{
  "posts": [
    {
      "id": "1",
      "title": "a title",
      "views": 100
    },
    {
      "id": "2",
      "title": "another title",
      "views": 200
    }
  ],
  "comments": [
    {
      "id": "1",
      "text": "a comment about post 1",
      "postId": "1"
    },
    {
      "id": "2",
      "text": "another comment about post 1",
      "postId": "1"
    }
  ],
  "profile": {
    "name": "typicode"
  },
  "students": [
    {
      "id": "2997",
      "name": "Fatma",
      "age": 26
    },
    {
      "id": "2225",
      "name": "Zafer AYAN",
      "age": 26
    },
    {
      "id": "0d01",
      "name": "Hasan",
      "age": 26
    },
    {
      "id": "f9eb",
      "name": "Serkan",
      "age": 26
    }
  ]
}